{"inkVersion":20,"root":[["ev","str","^Pandora","/str",{"x()":"Name","exArgs":1},"out","/ev","\n","ev","str","^Pandora","/str",{"x()":"Icon","exArgs":1},"out","/ev","\n","^Hello sweetheart! How are you?","\n","^Ready for your big debut?","\n","^Oh, I'm so excited to stream with a little cutie","\n","^like you! <3","\n","ev","str","^ Thank you for joining me!","/str","/ev",{"*":"0.c-0","flg":20},{"c-0":["^ ",{"->":"one"},"\n",{"->":"0.g-0"},{"#f":5}],"g-0":["done",{"#f":5}]}],"done",{"one":[["ev","str","^Pandora","/str",{"x()":"Name","exArgs":1},"out","/ev","\n","ev","str","^Pandora","/str",{"x()":"Icon","exArgs":1},"out","/ev","\n","^No need! I'm delighted to be here,","\n","^You better have lots of fun planned !","\n","^Though just being around you should be plenty <3","\n","ev","str","^ I'm just really nervous.. ","/str","/ev",{"*":".^.c-0","flg":20},"ev","str","^ You've got nothing to fear! ","/str","/ev",{"*":".^.c-1","flg":20},{"c-0":["^ ",{"->":"two"},"\n",{"#f":5}],"c-1":["^ ",{"->":"three"},"\n",{"#f":5}]}],{"#f":1}],"two":[["ev","str","^Pandora","/str",{"x()":"Name","exArgs":1},"out","/ev","\n","ev","str","^Pandora","/str",{"x()":"Icon","exArgs":1},"out","/ev","\n","^aww poor baby! no need to stress!","\n","^Everyones nervous for their first time.","\n","^Just relax, I'll catch you if you stumble!","\n","ev","str","^ We better start soon","/str","/ev",{"*":".^.c-0","flg":20},{"c-0":["^ ",{"->":"three"},"\n",{"#f":5}]}],{"#f":1}],"three":["ev","str","^Pandora","/str",{"x()":"Name","exArgs":1},"out","/ev","\n","ev","str","^Pandora","/str",{"x()":"Icon","exArgs":1},"out","/ev","\n","^Oooo, Loving the confidence!","\n","^Lead the way sweetheart!","\n","^I'll be watching~!","\n","end",{"#f":1}],"#f":1}],"listDefs":{}}